grotot/__init__.py
grotot/grotot.py
grotot/fns/__init__.py
grotot/fns/math_funcs.py
grotot-0.0.3.dist-info/METADATA
grotot-0.0.3.dist-info/WHEEL
grotot-0.0.3.dist-info/top_level.txt
grotot-0.0.3.dist-info/RECORD
